{
  "accentColor": "{{appsmith.theme.colors.primaryColor}}",
  "animateLoading": true,
  "borderColor": "#E0DEDE",
  "borderRadius": "{{appsmith.theme.borderRadius.appBorderRadius}}",
  "borderWidth": "1",
  "bottomRow": 30,
  "boxShadow": "{{appsmith.theme.boxShadow.appBoxShadow}}",
  "canFreezeColumn": true,
  "childStylesheet": {
    "button": {
      "borderRadius": "{{appsmith.theme.borderRadius.appBorderRadius}}",
      "boxShadow": "none",
      "buttonColor": "{{appsmith.theme.colors.primaryColor}}"
    },
    "editActions": {
      "discardBorderRadius": "{{appsmith.theme.borderRadius.appBorderRadius}}",
      "discardButtonColor": "{{appsmith.theme.colors.primaryColor}}",
      "saveBorderRadius": "{{appsmith.theme.borderRadius.appBorderRadius}}",
      "saveButtonColor": "{{appsmith.theme.colors.primaryColor}}"
    },
    "iconButton": {
      "borderRadius": "{{appsmith.theme.borderRadius.appBorderRadius}}",
      "boxShadow": "none",
      "buttonColor": "{{appsmith.theme.colors.primaryColor}}"
    },
    "menuButton": {
      "borderRadius": "{{appsmith.theme.borderRadius.appBorderRadius}}",
      "boxShadow": "none",
      "menuColor": "{{appsmith.theme.colors.primaryColor}}"
    }
  },
  "columnOrder": [
    "task_ordr",
    "task_id",
    "task_nm",
    "task_desc"
  ],
  "columnUpdatedAt": 1717767628719,
  "columnWidthMap": {
    "task_nm": 151,
    "task_ordr": 60,
    "value": 88
  },
  "compactMode": "SHORT",
  "defaultPageSize": 0,
  "defaultSelectedRowIndex": "0",
  "defaultSelectedRowIndices": [
    0
  ],
  "delimiter": ",",
  "displayName": "Table",
  "dynamicBindingPathList": [
    {
      "key": "accentColor"
    },
    {
      "key": "borderRadius"
    },
    {
      "key": "boxShadow"
    },
    {
      "key": "tableData"
    },
    {
      "key": "primaryColumns.task_ordr.computedValue"
    },
    {
      "key": "primaryColumns.task_id.computedValue"
    },
    {
      "key": "primaryColumns.task_nm.computedValue"
    },
    {
      "key": "primaryColumns.task_desc.computedValue"
    }
  ],
  "dynamicPropertyPathList": [
    {
      "key": "tableData"
    },
    {
      "key": "onRowSelected"
    }
  ],
  "dynamicTriggerPathList": [
    {
      "key": "onRowSelected"
    }
  ],
  "enableClientSideSearch": true,
  "flexVerticalAlignment": "start",
  "fontStyle": "",
  "hideCard": false,
  "horizontalAlignment": "LEFT",
  "iconSVG": "/static/media/icon.e6911f8bb94dc6c4a102a74740c41763.svg",
  "inlineEditingSaveOption": "ROW_LEVEL",
  "isDeprecated": false,
  "isLoading": false,
  "isSortable": true,
  "isVisible": true,
  "isVisibleDownload": false,
  "isVisibleFilters": false,
  "isVisiblePagination": false,
  "isVisibleSearch": false,
  "key": "rgly1h5mbe",
  "label": "Data",
  "leftColumn": 0,
  "minWidth": 450,
  "mobileBottomRow": 28,
  "mobileLeftColumn": 0,
  "mobileRightColumn": 34,
  "mobileTopRow": 0,
  "needsHeightForContent": true,
  "onRowSelected": "{{taskList.run()\nstoreValue('editMode','edit')}}",
  "originalBottomRow": 49,
  "originalTopRow": 23,
  "parentColumnSpace": 6.1796875,
  "parentId": "3udh40gmtx",
  "parentRowSpace": 10,
  "primaryColumnId": "task_id",
  "primaryColumns": {
    "task_desc": {
      "alias": "task_desc",
      "allowCellWrapping": false,
      "allowSameOptionsInNewRow": true,
      "cellBackground": "",
      "columnType": "text",
      "computedValue": "{{tbl_Tasks.processedTableData.map((currentRow, currentIndex) => ( currentRow[\"task_desc\"]))}}",
      "currencyCode": "USD",
      "decimals": 0,
      "enableFilter": true,
      "enableSort": true,
      "fontStyle": "",
      "horizontalAlignment": "LEFT",
      "id": "task_desc",
      "index": 2,
      "isCellEditable": false,
      "isCellVisible": true,
      "isDerived": false,
      "isDisabled": false,
      "isDiscardVisible": true,
      "isEditable": false,
      "isSaveVisible": true,
      "isVisible": true,
      "label": "Description",
      "notation": "standard",
      "originalId": "task_desc",
      "sticky": "",
      "textColor": "",
      "textSize": "0.875rem",
      "thousandSeparator": true,
      "validation": {},
      "verticalAlignment": "CENTER",
      "width": 150
    },
    "task_id": {
      "alias": "task_id",
      "allowCellWrapping": false,
      "allowSameOptionsInNewRow": true,
      "cellBackground": "",
      "columnType": "number",
      "computedValue": "{{tbl_Tasks.processedTableData.map((currentRow, currentIndex) => ( currentRow[\"task_id\"]))}}",
      "currencyCode": "USD",
      "decimals": 0,
      "enableFilter": true,
      "enableSort": true,
      "fontStyle": "",
      "horizontalAlignment": "LEFT",
      "id": "task_id",
      "index": 4,
      "isCellEditable": false,
      "isCellVisible": true,
      "isDerived": false,
      "isDisabled": false,
      "isDiscardVisible": true,
      "isEditable": false,
      "isSaveVisible": true,
      "isVisible": false,
      "label": "task_id",
      "notation": "standard",
      "originalId": "task_id",
      "sticky": "",
      "textColor": "",
      "textSize": "0.875rem",
      "thousandSeparator": true,
      "validation": {},
      "verticalAlignment": "CENTER",
      "width": 150
    },
    "task_nm": {
      "alias": "task_nm",
      "allowCellWrapping": false,
      "allowSameOptionsInNewRow": true,
      "cellBackground": "",
      "columnType": "text",
      "computedValue": "{{tbl_Tasks.processedTableData.map((currentRow, currentIndex) => ( currentRow[\"task_nm\"]))}}",
      "currencyCode": "USD",
      "decimals": 0,
      "enableFilter": true,
      "enableSort": true,
      "fontStyle": "",
      "horizontalAlignment": "LEFT",
      "id": "task_nm",
      "index": 1,
      "isCellEditable": false,
      "isCellVisible": true,
      "isDerived": false,
      "isDisabled": false,
      "isDiscardVisible": true,
      "isEditable": false,
      "isSaveVisible": true,
      "isVisible": true,
      "label": "Task",
      "notation": "standard",
      "originalId": "task_nm",
      "sticky": "",
      "textColor": "",
      "textSize": "0.875rem",
      "thousandSeparator": true,
      "validation": {},
      "verticalAlignment": "CENTER",
      "width": 150
    },
    "task_ordr": {
      "alias": "task_ordr",
      "allowCellWrapping": false,
      "allowSameOptionsInNewRow": true,
      "columnType": "number",
      "computedValue": "{{tbl_Tasks.processedTableData.map((currentRow, currentIndex) => ( currentRow[\"task_ordr\"]))}}",
      "currencyCode": "USD",
      "decimals": 0,
      "enableFilter": true,
      "enableSort": true,
      "fontStyle": "",
      "horizontalAlignment": "LEFT",
      "id": "task_ordr",
      "index": 0,
      "isCellEditable": false,
      "isCellVisible": true,
      "isDerived": false,
      "isDisabled": false,
      "isDiscardVisible": true,
      "isEditable": false,
      "isSaveVisible": true,
      "isVisible": true,
      "label": "",
      "notation": "standard",
      "originalId": "task_ordr",
      "sticky": "",
      "textSize": "0.875rem",
      "thousandSeparator": true,
      "validation": {},
      "verticalAlignment": "CENTER",
      "width": 150
    }
  },
  "renderMode": "CANVAS",
  "responsiveBehavior": "fill",
  "rightColumn": 64,
  "searchKey": "",
  "serverSidePaginationEnabled": true,
  "tableData": "{{taskList.data}}",
  "tags": [
    "Suggested",
    "Display"
  ],
  "textSize": "0.875rem",
  "topRow": 4,
  "totalRecordsCount": 0,
  "type": "TABLE_WIDGET_V2",
  "version": 2,
  "verticalAlignment": "CENTER",
  "widgetId": "15mgfy38dk",
  "widgetName": "tbl_Tasks"
}