{
  "gitSyncId": "6664696488cf8166d347ad0a_ef8bf2ec-d0ae-4bda-935e-746cbcaaf687",
  "id": "Products_jsTabs.resetTabs",
  "pluginId": "js-plugin",
  "pluginType": "JS",
  "unpublishedAction": {
    "actionConfiguration": {
      "encodeParamsToggle": true,
      "jsArguments": [],
      "paginationType": "NONE",
      "timeoutInMillisecond": 10000
    },
    "clientSideExecution": true,
    "collectionId": "Products_jsTabs",
    "confirmBeforeExecute": false,
    "datasource": {
      "isAutoGenerated": false,
      "name": "UNUSED_DATASOURCE",
      "pluginId": "js-plugin"
    },
    "dynamicBindingPathList": [
      {
        "key": "body"
      }
    ],
    "executeOnLoad": false,
    "fullyQualifiedName": "jsTabs.resetTabs",
    "name": "resetTabs",
    "pageId": "Products",
    "userSetOnLoad": false
  }
}