{
  "animateLoading": true,
  "autoGenerateForm": false,
  "backgroundColor": "#f4f4f5",
  "borderColor": "#E0DEDE",
  "borderRadius": "1.5rem",
  "borderWidth": "1",
  "bottomRow": 49,
  "boxShadow": "{{appsmith.theme.boxShadow.appBoxShadow}}",
  "childStylesheet": {
    "ARRAY": {
      "accentColor": "{{appsmith.theme.colors.primaryColor}}",
      "borderRadius": "{{appsmith.theme.borderRadius.appBorderRadius}}",
      "boxShadow": "none",
      "cellBorderRadius": "{{appsmith.theme.borderRadius.appBorderRadius}}",
      "cellBoxShadow": "none"
    },
    "CHECKBOX": {
      "accentColor": "{{appsmith.theme.colors.primaryColor}}",
      "borderRadius": "{{appsmith.theme.borderRadius.appBorderRadius}}"
    },
    "CURRENCY_INPUT": {
      "accentColor": "{{appsmith.theme.colors.primaryColor}}",
      "borderRadius": "{{appsmith.theme.borderRadius.appBorderRadius}}",
      "boxShadow": "none"
    },
    "DATEPICKER": {
      "accentColor": "{{appsmith.theme.colors.primaryColor}}",
      "borderRadius": "{{appsmith.theme.borderRadius.appBorderRadius}}",
      "boxShadow": "none"
    },
    "EMAIL_INPUT": {
      "accentColor": "{{appsmith.theme.colors.primaryColor}}",
      "borderRadius": "{{appsmith.theme.borderRadius.appBorderRadius}}",
      "boxShadow": "none"
    },
    "MULTILINE_TEXT_INPUT": {
      "accentColor": "{{appsmith.theme.colors.primaryColor}}",
      "borderRadius": "{{appsmith.theme.borderRadius.appBorderRadius}}",
      "boxShadow": "none"
    },
    "MULTISELECT": {
      "accentColor": "{{appsmith.theme.colors.primaryColor}}",
      "borderRadius": "{{appsmith.theme.borderRadius.appBorderRadius}}",
      "boxShadow": "none"
    },
    "NUMBER_INPUT": {
      "accentColor": "{{appsmith.theme.colors.primaryColor}}",
      "borderRadius": "{{appsmith.theme.borderRadius.appBorderRadius}}",
      "boxShadow": "none"
    },
    "OBJECT": {
      "borderRadius": "{{appsmith.theme.borderRadius.appBorderRadius}}",
      "boxShadow": "none",
      "cellBorderRadius": "{{appsmith.theme.borderRadius.appBorderRadius}}",
      "cellBoxShadow": "none"
    },
    "PASSWORD_INPUT": {
      "accentColor": "{{appsmith.theme.colors.primaryColor}}",
      "borderRadius": "{{appsmith.theme.borderRadius.appBorderRadius}}",
      "boxShadow": "none"
    },
    "PHONE_NUMBER_INPUT": {
      "accentColor": "{{appsmith.theme.colors.primaryColor}}",
      "borderRadius": "{{appsmith.theme.borderRadius.appBorderRadius}}",
      "boxShadow": "none"
    },
    "RADIO_GROUP": {
      "accentColor": "{{appsmith.theme.colors.primaryColor}}",
      "boxShadow": "none"
    },
    "SELECT": {
      "accentColor": "{{appsmith.theme.colors.primaryColor}}",
      "borderRadius": "{{appsmith.theme.borderRadius.appBorderRadius}}",
      "boxShadow": "none"
    },
    "SWITCH": {
      "accentColor": "{{appsmith.theme.colors.primaryColor}}",
      "boxShadow": "none"
    },
    "TEXT_INPUT": {
      "accentColor": "{{appsmith.theme.colors.primaryColor}}",
      "borderRadius": "{{appsmith.theme.borderRadius.appBorderRadius}}",
      "boxShadow": "none"
    }
  },
  "disabledWhenInvalid": true,
  "displayName": "JSON Form",
  "dynamicBindingPathList": [
    {
      "key": "boxShadow"
    },
    {
      "key": "submitButtonStyles.buttonColor"
    },
    {
      "key": "submitButtonStyles.borderRadius"
    },
    {
      "key": "resetButtonStyles.buttonColor"
    },
    {
      "key": "resetButtonStyles.borderRadius"
    },
    {
      "key": "sourceData"
    },
    {
      "key": "schema.__root_schema__.children.ingr_ordr.defaultValue"
    },
    {
      "key": "schema.__root_schema__.children.ingr_ordr.accentColor"
    },
    {
      "key": "schema.__root_schema__.children.ingr_ordr.borderRadius"
    },
    {
      "key": "schema.__root_schema__.children.ingr_name.defaultValue"
    },
    {
      "key": "schema.__root_schema__.children.ingr_name.accentColor"
    },
    {
      "key": "schema.__root_schema__.children.ingr_name.borderRadius"
    },
    {
      "key": "schema.__root_schema__.children.ingr_qty.defaultValue"
    },
    {
      "key": "schema.__root_schema__.children.ingr_qty.accentColor"
    },
    {
      "key": "schema.__root_schema__.children.ingr_qty.borderRadius"
    },
    {
      "key": "schema.__root_schema__.children.ingr_meas.defaultValue"
    },
    {
      "key": "schema.__root_schema__.children.ingr_meas.accentColor"
    },
    {
      "key": "schema.__root_schema__.children.ingr_meas.borderRadius"
    },
    {
      "key": "schema.__root_schema__.children.ingr_id.defaultValue"
    },
    {
      "key": "schema.__root_schema__.children.ingr_id.accentColor"
    },
    {
      "key": "schema.__root_schema__.children.ingr_id.borderRadius"
    },
    {
      "key": "schema.__root_schema__.children.prd_rcpe_uuid.defaultValue"
    },
    {
      "key": "schema.__root_schema__.children.prd_rcpe_uuid.accentColor"
    },
    {
      "key": "schema.__root_schema__.children.prd_rcpe_uuid.borderRadius"
    },
    {
      "key": "schema.__root_schema__.defaultValue"
    },
    {
      "key": "schema.__root_schema__.borderRadius"
    },
    {
      "key": "schema.__root_schema__.cellBorderRadius"
    },
    {
      "key": "schema.__root_schema__.children.ingr_meas_id.defaultValue"
    },
    {
      "key": "schema.__root_schema__.children.ingr_meas_id.accentColor"
    },
    {
      "key": "schema.__root_schema__.children.ingr_meas_id.borderRadius"
    },
    {
      "key": "schema.__root_schema__.children.ingr_meas_id.options"
    },
    {
      "key": "schema.__root_schema__.children.customField1.accentColor"
    },
    {
      "key": "schema.__root_schema__.children.customField1.borderRadius"
    },
    {
      "key": "schema.__root_schema__.children.ingr_type_id.defaultValue"
    },
    {
      "key": "schema.__root_schema__.children.ingr_type_id.accentColor"
    },
    {
      "key": "schema.__root_schema__.children.ingr_type_id.borderRadius"
    },
    {
      "key": "schema.__root_schema__.children.ingr_type_id.options"
    },
    {
      "key": "schema.__root_schema__.children.ingr_id.options"
    },
    {
      "key": "schema.__root_schema__.children.comments.defaultValue"
    },
    {
      "key": "schema.__root_schema__.children.comments.borderRadius"
    },
    {
      "key": "schema.__root_schema__.children.comments.accentColor"
    }
  ],
  "dynamicHeight": "FIXED",
  "dynamicPropertyPathList": [
    {
      "key": "schema.__root_schema__.children.customField1.onOptionChange"
    },
    {
      "key": "schema.__root_schema__.children.ingr_type_id.onOptionChange"
    },
    {
      "key": "onSubmit"
    }
  ],
  "dynamicTriggerPathList": [
    {
      "key": "schema.__root_schema__.children.customField1.onOptionChange"
    },
    {
      "key": "schema.__root_schema__.children.ingr_type_id.onOptionChange"
    },
    {
      "key": "onSubmit"
    }
  ],
  "fieldLimitExceeded": false,
  "fixedFooter": true,
  "flexVerticalAlignment": "start",
  "hideCard": false,
  "iconSVG": "/static/media/icon.7df6f087cceba86a9a5481b6c7f4871d.svg",
  "isDeprecated": false,
  "isLoading": false,
  "isVisible": true,
  "key": "j241ugu9j9",
  "leftColumn": 0,
  "maxDynamicHeight": 9000,
  "minDynamicHeight": 4,
  "minWidth": 450,
  "mobileBottomRow": 74,
  "mobileLeftColumn": 1,
  "mobileRightColumn": 26,
  "mobileTopRow": 33,
  "needsErrorInfo": false,
  "onCanvasUI": {
    "disableParentSelection": false,
    "focusBGCSSVar": "--on-canvas-ui-widget-focus",
    "focusColorCSSVar": "--on-canvas-ui-widget-selection",
    "selectionBGCSSVar": "--on-canvas-ui-widget-selection",
    "selectionColorCSSVar": "--on-canvas-ui-widget-focus"
  },
  "onSubmit": "{{ingr_Edit.run()\ningr_List.run()\njsRecipe.editMode('Back')}}",
  "originalBottomRow": 109,
  "originalTopRow": 68,
  "parentColumnSpace": 6.4921875,
  "parentId": "7c1kxprgur",
  "parentRowSpace": 10,
  "renderMode": "CANVAS",
  "resetButtonLabel": "Reset",
  "resetButtonStyles": {
    "borderRadius": "{{appsmith.theme.borderRadius.appBorderRadius}}",
    "boxShadow": "none",
    "buttonColor": "{{appsmith.theme.colors.primaryColor}}",
    "buttonVariant": "SECONDARY"
  },
  "responsiveBehavior": "fill",
  "rightColumn": 64,
  "schema": {
    "__root_schema__": {
      "accessor": "__root_schema__",
      "borderRadius": "{{((sourceData, formData, fieldState) => ((appsmith.theme.borderRadius.appBorderRadius)))(jsnRecipe.sourceData, jsnRecipe.formData, jsnRecipe.fieldState)}}",
      "boxShadow": "none",
      "cellBorderRadius": "{{((sourceData, formData, fieldState) => ((appsmith.theme.borderRadius.appBorderRadius)))(jsnRecipe.sourceData, jsnRecipe.formData, jsnRecipe.fieldState)}}",
      "cellBoxShadow": "none",
      "children": {
        "comments": {
          "accentColor": "{{((sourceData, formData, fieldState) => ((appsmith.theme.colors.primaryColor)))(jsnRecipe.sourceData, jsnRecipe.formData, jsnRecipe.fieldState)}}",
          "accessor": "comments",
          "borderRadius": "{{((sourceData, formData, fieldState) => ((appsmith.theme.borderRadius.appBorderRadius)))(jsnRecipe.sourceData, jsnRecipe.formData, jsnRecipe.fieldState)}}",
          "boxShadow": "none",
          "children": {},
          "dataType": "string",
          "defaultValue": "{{((sourceData, formData, fieldState) => (sourceData.comments))(jsnRecipe.sourceData, jsnRecipe.formData, jsnRecipe.fieldState)}}",
          "fieldType": "Multiline Text Input",
          "iconAlign": "left",
          "identifier": "comments",
          "isCustomField": false,
          "isDisabled": false,
          "isRequired": false,
          "isSpellCheck": false,
          "isVisible": true,
          "label": "Comments",
          "labelTextSize": "0.875rem",
          "originalIdentifier": "comments",
          "position": 9,
          "sourceData": ""
        },
        "customField1": {
          "accentColor": "{{((sourceData, formData, fieldState) => ((appsmith.theme.colors.primaryColor)))(jsnRecipe.sourceData, jsnRecipe.formData, jsnRecipe.fieldState)}}",
          "accessor": "editMode",
          "borderRadius": "{{((sourceData, formData, fieldState) => ((appsmith.theme.borderRadius.appBorderRadius)))(jsnRecipe.sourceData, jsnRecipe.formData, jsnRecipe.fieldState)}}",
          "boxShadow": "none",
          "children": {},
          "dataType": "string",
          "defaultValue": "Edit",
          "fieldType": "Select",
          "identifier": "customField1",
          "isCustomField": true,
          "isDisabled": false,
          "isFilterable": false,
          "isRequired": false,
          "isVisible": true,
          "label": "Edit, Add, Delete or Return",
          "labelTextSize": "0.875rem",
          "onOptionChange": "{{jsRecipe.editMode(jsnRecipe.formData.editMode)}}",
          "options": "[\n  {\n    \"label\": \"Edit\",\n    \"value\": \"Edit\"\n  },\n  {\n    \"label\": \"Add\",\n    \"value\": \"Add\"\n  },\n  {\n    \"label\": \"Delete\",\n    \"value\": \"Delete\"\n  },\n  {\n    \"label\": \"Back To Recipes\",\n    \"value\": \"Back\"\n  }\n]",
          "originalIdentifier": "customField1",
          "position": 0,
          "serverSideFiltering": false,
          "sourceData": ""
        },
        "ingr_id": {
          "accentColor": "{{((sourceData, formData, fieldState) => ((appsmith.theme.colors.primaryColor)))(jsnRecipe.sourceData, jsnRecipe.formData, jsnRecipe.fieldState)}}",
          "accessor": "ingr_id",
          "borderRadius": "{{((sourceData, formData, fieldState) => ((appsmith.theme.borderRadius.appBorderRadius)))(jsnRecipe.sourceData, jsnRecipe.formData, jsnRecipe.fieldState)}}",
          "boxShadow": "none",
          "children": {},
          "dataType": "number",
          "defaultValue": "{{((sourceData, formData, fieldState) => (sourceData.ingr_id))(jsnRecipe.sourceData, jsnRecipe.formData, jsnRecipe.fieldState)}}",
          "fieldType": "Select",
          "identifier": "ingr_id",
          "isCustomField": false,
          "isDisabled": false,
          "isFilterable": false,
          "isRequired": false,
          "isVisible": true,
          "label": "Ingredient",
          "labelTextSize": "0.875rem",
          "options": "{{ingr_dd.data}}",
          "originalIdentifier": "ingr_id",
          "position": 2,
          "serverSideFiltering": false,
          "sourceData": 4
        },
        "ingr_meas": {
          "accentColor": "{{((sourceData, formData, fieldState) => ((appsmith.theme.colors.primaryColor)))(jsnRecipe.sourceData, jsnRecipe.formData, jsnRecipe.fieldState)}}",
          "accessor": "ingr_meas",
          "borderRadius": "{{((sourceData, formData, fieldState) => ((appsmith.theme.borderRadius.appBorderRadius)))(jsnRecipe.sourceData, jsnRecipe.formData, jsnRecipe.fieldState)}}",
          "boxShadow": "none",
          "children": {},
          "dataType": "string",
          "defaultValue": "{{((sourceData, formData, fieldState) => (sourceData.ingr_meas))(jsnRecipe.sourceData, jsnRecipe.formData, jsnRecipe.fieldState)}}",
          "fieldType": "Text Input",
          "iconAlign": "left",
          "identifier": "ingr_meas",
          "isCustomField": false,
          "isDisabled": false,
          "isRequired": false,
          "isSpellCheck": false,
          "isVisible": false,
          "label": "Ingr Meas",
          "labelTextSize": "0.875rem",
          "originalIdentifier": "ingr_meas",
          "position": 7,
          "sourceData": "-"
        },
        "ingr_meas_id": {
          "accentColor": "{{((sourceData, formData, fieldState) => ((appsmith.theme.colors.primaryColor)))(jsnRecipe.sourceData, jsnRecipe.formData, jsnRecipe.fieldState)}}",
          "accessor": "ingr_meas_id",
          "borderRadius": "{{((sourceData, formData, fieldState) => ((appsmith.theme.borderRadius.appBorderRadius)))(jsnRecipe.sourceData, jsnRecipe.formData, jsnRecipe.fieldState)}}",
          "boxShadow": "none",
          "children": {},
          "dataType": "number",
          "defaultValue": "{{((sourceData, formData, fieldState) => (sourceData.ingr_meas_id))(jsnRecipe.sourceData, jsnRecipe.formData, jsnRecipe.fieldState)}}",
          "fieldType": "Select",
          "identifier": "ingr_meas_id",
          "isCustomField": false,
          "isDisabled": false,
          "isFilterable": false,
          "isRequired": false,
          "isVisible": true,
          "label": "Units",
          "labelTextSize": "0.875rem",
          "options": "{{measure_dd.data}}",
          "originalIdentifier": "ingr_meas_id",
          "position": 6,
          "serverSideFiltering": false,
          "sourceData": 51
        },
        "ingr_name": {
          "accentColor": "{{((sourceData, formData, fieldState) => ((appsmith.theme.colors.primaryColor)))(jsnRecipe.sourceData, jsnRecipe.formData, jsnRecipe.fieldState)}}",
          "accessor": "ingr_name",
          "borderRadius": "{{((sourceData, formData, fieldState) => ((appsmith.theme.borderRadius.appBorderRadius)))(jsnRecipe.sourceData, jsnRecipe.formData, jsnRecipe.fieldState)}}",
          "boxShadow": "none",
          "children": {},
          "dataType": "string",
          "defaultValue": "{{((sourceData, formData, fieldState) => (sourceData.ingr_name))(jsnRecipe.sourceData, jsnRecipe.formData, jsnRecipe.fieldState)}}",
          "fieldType": "Text Input",
          "iconAlign": "left",
          "identifier": "ingr_name",
          "isCustomField": false,
          "isDisabled": false,
          "isRequired": false,
          "isSpellCheck": false,
          "isVisible": false,
          "label": "Ingr Name",
          "labelTextSize": "0.875rem",
          "originalIdentifier": "ingr_name",
          "position": 4,
          "sourceData": "Cucumbers"
        },
        "ingr_ordr": {
          "accentColor": "{{((sourceData, formData, fieldState) => ((appsmith.theme.colors.primaryColor)))(jsnRecipe.sourceData, jsnRecipe.formData, jsnRecipe.fieldState)}}",
          "accessor": "ingr_ordr",
          "borderRadius": "{{((sourceData, formData, fieldState) => ((appsmith.theme.borderRadius.appBorderRadius)))(jsnRecipe.sourceData, jsnRecipe.formData, jsnRecipe.fieldState)}}",
          "boxShadow": "none",
          "children": {},
          "dataType": "number",
          "defaultValue": "{{((sourceData, formData, fieldState) => (sourceData.ingr_ordr))(jsnRecipe.sourceData, jsnRecipe.formData, jsnRecipe.fieldState)}}",
          "fieldType": "Number Input",
          "iconAlign": "left",
          "identifier": "ingr_ordr",
          "isCustomField": false,
          "isDisabled": false,
          "isRequired": false,
          "isSpellCheck": false,
          "isVisible": true,
          "label": "Ingr Ordr",
          "labelTextSize": "0.875rem",
          "originalIdentifier": "ingr_ordr",
          "position": 3,
          "sourceData": 40
        },
        "ingr_qty": {
          "accentColor": "{{((sourceData, formData, fieldState) => ((appsmith.theme.colors.primaryColor)))(jsnRecipe.sourceData, jsnRecipe.formData, jsnRecipe.fieldState)}}",
          "accessor": "ingr_qty",
          "borderRadius": "{{((sourceData, formData, fieldState) => ((appsmith.theme.borderRadius.appBorderRadius)))(jsnRecipe.sourceData, jsnRecipe.formData, jsnRecipe.fieldState)}}",
          "boxShadow": "none",
          "children": {},
          "dataType": "number",
          "defaultValue": "{{((sourceData, formData, fieldState) => (sourceData.ingr_qty))(jsnRecipe.sourceData, jsnRecipe.formData, jsnRecipe.fieldState)}}",
          "fieldType": "Number Input",
          "iconAlign": "left",
          "identifier": "ingr_qty",
          "isCustomField": false,
          "isDisabled": false,
          "isRequired": false,
          "isSpellCheck": false,
          "isVisible": true,
          "label": "Ingr Qty",
          "labelTextSize": "0.875rem",
          "originalIdentifier": "ingr_qty",
          "position": 5,
          "sourceData": 0
        },
        "ingr_type_id": {
          "accentColor": "{{((sourceData, formData, fieldState) => ((appsmith.theme.colors.primaryColor)))(jsnRecipe.sourceData, jsnRecipe.formData, jsnRecipe.fieldState)}}",
          "accessor": "ingr_type_id",
          "borderRadius": "{{((sourceData, formData, fieldState) => ((appsmith.theme.borderRadius.appBorderRadius)))(jsnRecipe.sourceData, jsnRecipe.formData, jsnRecipe.fieldState)}}",
          "boxShadow": "none",
          "children": {},
          "dataType": "number",
          "defaultValue": "{{((sourceData, formData, fieldState) => (sourceData.ingr_type_id))(jsnRecipe.sourceData, jsnRecipe.formData, jsnRecipe.fieldState)}}",
          "fieldType": "Select",
          "identifier": "ingr_type_id",
          "isCustomField": false,
          "isDisabled": false,
          "isFilterable": false,
          "isRequired": false,
          "isVisible": true,
          "label": "Ingredient Type",
          "labelTextSize": "0.875rem",
          "onOptionChange": "{{await storeValue('ingrTypeID',jsnRecipe.formData.ingr_type_id)\nawait ingr_dd.run()}}",
          "options": "{{ingrType_dd.data}}",
          "originalIdentifier": "ingr_type_id",
          "position": 1,
          "serverSideFiltering": false,
          "sourceData": 3
        },
        "prd_rcpe_uuid": {
          "accentColor": "{{((sourceData, formData, fieldState) => ((appsmith.theme.colors.primaryColor)))(jsnRecipe.sourceData, jsnRecipe.formData, jsnRecipe.fieldState)}}",
          "accessor": "prd_rcpe_uuid",
          "borderRadius": "{{((sourceData, formData, fieldState) => ((appsmith.theme.borderRadius.appBorderRadius)))(jsnRecipe.sourceData, jsnRecipe.formData, jsnRecipe.fieldState)}}",
          "boxShadow": "none",
          "children": {},
          "dataType": "string",
          "defaultValue": "{{((sourceData, formData, fieldState) => (sourceData.prd_rcpe_uuid))(jsnRecipe.sourceData, jsnRecipe.formData, jsnRecipe.fieldState)}}",
          "fieldType": "Text Input",
          "iconAlign": "left",
          "identifier": "prd_rcpe_uuid",
          "isCustomField": false,
          "isDisabled": false,
          "isRequired": false,
          "isSpellCheck": false,
          "isVisible": false,
          "label": "Prd Rcpe Uuid",
          "labelTextSize": "0.875rem",
          "originalIdentifier": "prd_rcpe_uuid",
          "position": 8,
          "sourceData": "7074ae53-5fd3-11e9-afbe-0401b448d301"
        }
      },
      "dataType": "object",
      "defaultValue": "{{((sourceData, formData, fieldState) => (sourceData))(jsnRecipe.sourceData, jsnRecipe.formData, jsnRecipe.fieldState)}}",
      "fieldType": "Object",
      "identifier": "__root_schema__",
      "isCustomField": false,
      "isDisabled": false,
      "isRequired": false,
      "isVisible": true,
      "label": "",
      "labelTextSize": "0.875rem",
      "originalIdentifier": "__root_schema__",
      "position": -1,
      "sourceData": {
        "comments": "",
        "ingr_id": 4,
        "ingr_meas": "-",
        "ingr_meas_id": 51,
        "ingr_name": "Cucumbers",
        "ingr_ordr": 40,
        "ingr_qty": 0,
        "ingr_type_id": 3,
        "prd_rcpe_uuid": "7074ae53-5fd3-11e9-afbe-0401b448d301"
      }
    }
  },
  "scrollContents": true,
  "showReset": true,
  "sourceData": "{{tbl_Recipe.selectedRow}}",
  "submitButtonLabel": "Submit",
  "submitButtonStyles": {
    "borderRadius": "{{appsmith.theme.borderRadius.appBorderRadius}}",
    "boxShadow": "none",
    "buttonColor": "{{appsmith.theme.colors.primaryColor}}",
    "buttonVariant": "PRIMARY"
  },
  "tags": [
    "Suggested",
    "Layout"
  ],
  "thumbnailSVG": "/static/media/thumbnail.1092bbfe332a9ea2da2aa7e3efd01db2.svg",
  "title": "",
  "topRow": 0,
  "type": "JSON_FORM_WIDGET",
  "useSourceData": true,
  "version": 1,
  "widgetId": "i3r4h6zm2u",
  "widgetName": "jsnRecipe"
}